blaupause/__init__.py
blaupause/__main__.py
blaupause/blueprint.py
blaupause/functions.py
blaupause/tests/__init__.py
blaupause/tests/test_function.py
blaupause-0.1.17.dist-info/METADATA
blaupause-0.1.17.dist-info/WHEEL
blaupause-0.1.17.dist-info/licenses/LICENSE
blaupause-0.1.17.dist-info/RECORD
