Metadata-Version: 2.4
Name: blaupause
Version: 0.1.17
Summary: Example package used as a template for setting up Python packages/repositories.
Project-URL: Homepage, https://github.com/lang-m/blaupause
Author: Martin Lang, Marijan Beg
License-Expression: BSD-3-Clause
License-File: LICENSE
Requires-Python: >=3.8
Requires-Dist: pytest
